{
    "modelPackage": "factset.analyticsapi.engines.v2.models",
    "apiPackage": "factset.analyticsapi.engines.v2.api",
    "invokerPackage": "factset.analyticsapi.engines.v2",
    "groupId": "com.factset.analyticsapi",
    "artifactId": "engines-java-sdk-v2",
    "artifactVersion": "2.0.0",
    "artifactUrl": "",
    "artifactDescription": "SDK for v2 Engines API version",
    "scmConnection": "",
    "scmDeveloperConnection": "",
    "scmUrl": "",
    "developerName": "Analytics API",
    "developerEmail": "analytics.api.support@factset.com",
    "developerOrganization": "FactSet Research Systems Inc.",
    "developerOrganizationUrl": "https://developer.factset.com/",
    "licenseName": "The Apache Software License, Version 2.0",
    "licenseUrl": "http://www.apache.org/licenses/LICENSE-2.0.txt",
    "serializableModel": true,
    "fullJavaUtil": true,
    "withXml": false,
    "useGzipFeature": false,
    "hideGenerationTimestamp": true,
    "caseInsensitiveResponseHeaders": true,
    "library": "jersey2"
}